google_music/__about__.py
google_music/__init__.py
google_music/api.py
google_music/clients/__init__.py
google_music/clients/base.py
google_music/clients/mobileclient.py
google_music/clients/musicmanager.py
google_music/sessions.py
google_music/token_handlers.py
google_music/utils.py
google_music-3.7.0.dist-info/LICENSE
google_music-3.7.0.dist-info/WHEEL
google_music-3.7.0.dist-info/METADATA
google_music-3.7.0.dist-info/RECORD
