Metadata-Version: 2.1
Name: google-music
Version: 3.7.0
Summary: A Google Music API wrapper.
Home-page: https://github.com/thebigmunch/google-music
License: MIT
Author: thebigmunch
Author-email: mail@thebigmunch.me
Requires-Python: >=3.6,<4.0
Classifier: License :: OSI Approved :: MIT License
Classifier: Programming Language :: Python :: 3
Classifier: Programming Language :: Python :: 3.6
Classifier: Programming Language :: Python :: 3.7
Classifier: Programming Language :: Python :: 3.8
Provides-Extra: dev
Provides-Extra: doc
Provides-Extra: lint
Requires-Dist: appdirs (>=1.0,<2.0)
Requires-Dist: audio-metadata (>=0.10)
Requires-Dist: flake8 (>=3.5,<4.0); extra == "dev" or extra == "lint"
Requires-Dist: flake8-builtins (>=1.0,<2.0); extra == "dev" or extra == "lint"
Requires-Dist: flake8-comprehensions (>=2.0,<=4.0); extra == "dev" or extra == "lint"
Requires-Dist: flake8-import-order (>=0.18,<0.19); extra == "dev" or extra == "lint"
Requires-Dist: flake8-import-order-tbm (>=1.0,<2.0); extra == "dev" or extra == "lint"
Requires-Dist: google-music-proto (>=2.8.0,<3.0.0)
Requires-Dist: httpx (>=0.11,<1.0)
Requires-Dist: nox (>=2019,<2020); extra == "dev"
Requires-Dist: oauthlib (>=3.0,<4.0)
Requires-Dist: protobuf (>=3.5,<4.0)
Requires-Dist: sphinx (>=2.0,<3.0); extra == "dev" or extra == "doc"
Requires-Dist: sphinx-material (<1.0.0); extra == "dev" or extra == "doc"
Requires-Dist: tbm-utils (>=2.4,<3.0)
Requires-Dist: tenacity (>=5.0,<7.0)
Requires-Dist: wrapt (>=1.0,<2.0)
Project-URL: Repository, https://github.com/thebigmunch/google-music
